py_test_server_358-0.1.2.data/scripts/server_run.py
server/__init__.py
server/server.py
server/server_run.py
server/common/__init__.py
server/common/decos.py
server/common/descriptors.py
server/common/errors.py
server/common/metaclasses.py
server/common/utils.py
server/common/variables.py
server/doc/__init__.py
server/doc/source/__init__.py
server/doc/source/conf.py
server/logs/__init__.py
server/logs/config_client_log.py
server/logs/config_server_log.py
server/server/__init__.py
server/server/add_user.py
server/server/config_window.py
server/server/core.py
server/server/main_window.py
server/server/remove_user.py
server/server/server_database.py
server/server/stat_window.py
server/unit_tests/__init__.py
server/unit_tests/test_client.py
server/unit_tests/test_utils.py
py_test_server_358-0.1.2.dist-info/METADATA
py_test_server_358-0.1.2.dist-info/WHEEL
py_test_server_358-0.1.2.dist-info/top_level.txt
py_test_server_358-0.1.2.dist-info/RECORD
